{
    "id": "2",
    "subid": "12",
    "dataflow": "sedimentation",
    "transformation": "solversimulationfluid",
    "workspace": "/Users/vitor/Documents/Repository/Thesis/Workflow-Sedimentation/sedimentation",
    "status": "FINISHED",
    "performances": [
        {
            "description": "libMeshSedimentation::solversimulationfluid-1-12",
            "method": "COMPUTATION",
            "endTime": "05.09.2016-11:28:34"
        }
    ],
    "sets": [
        {
            "tag": "osolversimulationfluid",
            "elements": [
                "1;1;0.02;0;4;200;0.00;0.00;0.00;false"
            ]
        }
    ],
    "dependency": {
        "tags": [
            {
                "tag": "getmaximumiterations"
            }
        ],
        "ids": [
            {
                "id": "1"
            }
        ]
    },
    "files": []
}
